{
  "checked_at_local": "2026-06-06T20:01:35-07:00",
  "publishable_timing_allowed": false,
  "rows": [
    {
      "blockers": [
        "/System/Library/PrivateFrameworks/MediaAnalysis.framework/Versions/A/mediaanalysisd at 9.6% CPU",
        "swap used 270.12 MB exceeds 0.0 MB"
      ],
      "load": {
        "fifteen_minutes": 2.5,
        "five_minutes": 2.07,
        "one_minute": 1.5
      },
      "machine_id": "irvine-m1",
      "memory_pressure": {
        "free_pct": 74,
        "raw": "The system has 17179869184 (1048576 pages with a page size of 16384).\n\nStats: \nPages free: 14332 \nPages purgeable: 11597 \nPages purged: 71590647 \n\nSwap I/O:\nSwapins: 132860 \nSwapouts: 793805 \n\nPage Q counts:\nPages active: 367696 \nPages inactive: 339083 \nPages speculative: 28447 \nPages throttled: 0 \nPages wired down: 144627 \n\nCompressor Stats:\nPages used by compressor: 108294 \nPages decompressed: 700514037 \nPages compressed: 787562668 \n\nFile I/O:\nPageins: 1023424254 \nPageouts: 3924252 \n\nSystem-wide memory free percentage: 74%"
      },
      "ok": true,
      "power": {
        "ac_power": true,
        "raw": "Now drawing from 'AC Power'"
      },
      "processes": [
        {
          "command": "sshd-session: mattmireles [priv]",
          "cpu_pct": 13.0,
          "noisy": false
        },
        {
          "command": "/System/Library/PrivateFrameworks/DataAccess.framework/Support/dataaccessd",
          "cpu_pct": 10.4,
          "noisy": false
        },
        {
          "command": "/System/Library/PrivateFrameworks/MediaAnalysis.framework/Versions/A/mediaanalysisd",
          "cpu_pct": 9.6,
          "noisy": true
        },
        {
          "command": "/System/Library/PrivateFrameworks/AOSKit.framework/Versions/A/XPCServices/com.apple.iCloudHelper.xpc/Contents/MacOS/com.apple.iCloudHelper",
          "cpu_pct": 9.1,
          "noisy": false
        },
        {
          "command": "/usr/libexec/trustd",
          "cpu_pct": 6.1,
          "noisy": false
        },
        {
          "command": "/usr/libexec/opendirectoryd",
          "cpu_pct": 3.5,
          "noisy": false
        },
        {
          "command": "/usr/libexec/lsd",
          "cpu_pct": 3.0,
          "noisy": false
        },
        {
          "command": "/System/Library/PrivateFrameworks/SkyLight.framework/Resources/WindowServer",
          "cpu_pct": 1.6,
          "noisy": false
        },
        {
          "command": "/Applications/Usage.app/Contents/MacOS/Usage Background Service.app/Contents/MacOS/Usage Background Service",
          "cpu_pct": 1.6,
          "noisy": false
        },
        {
          "command": "/System/Library/DriverExtensions/com.apple.DriverKit-AppleBCMWLAN.dext/com.apple.DriverKit-AppleBCMWLAN",
          "cpu_pct": 1.5,
          "noisy": false
        },
        {
          "command": "/sbin/launchd",
          "cpu_pct": 1.2,
          "noisy": false
        },
        {
          "command": "/Applications/Botnet.app/Contents/MacOS/Brave Browser",
          "cpu_pct": 1.2,
          "noisy": false
        }
      ],
      "quiet": false,
      "swap": {
        "raw": "vm.swapusage: total = 1024.00M  used = 270.12M  free = 753.88M  (encrypted)",
        "used_mb": 270.12
      },
      "target": "mattmireles@irvine-m1.local",
      "thermal": {
        "ok": true,
        "raw": "Note: No thermal warning level has been recorded\nNote: No performance warning level has been recorded\nNote: No CPU power status has been recorded"
      },
      "thresholds": {
        "max_load_1": 1.5,
        "max_noisy_cpu_pct": 5.0,
        "max_swap_used_mb": 0.0,
        "min_memory_free_pct": 10,
        "noisy_process_patterns": [
          "mds",
          "mdworker",
          "mediaanalysisd",
          "mediaanalysisd-access",
          "photoanalysisd"
        ],
        "require_ac_power": true
      },
      "uptime": "20:01  up 7 days,  5:01, 1 user, load averages: 1.50 2.07 2.50"
    },
    {
      "blockers": [
        "load1 2.35 exceeds 1.50",
        "swap used 266.94 MB exceeds 0.0 MB",
        "not drawing from AC power"
      ],
      "load": {
        "fifteen_minutes": 3.7,
        "five_minutes": 3.35,
        "one_minute": 2.35
      },
      "machine_id": "m2-air",
      "memory_pressure": {
        "free_pct": 58,
        "raw": "The system has 25769803776 (1572864 pages with a page size of 16384).\n\nStats: \nPages free: 4184 \nPages purgeable: 6862 \nPages purged: 22160862 \n\nSwap I/O:\nSwapins: 12035476 \nSwapouts: 12997454 \n\nPage Q counts:\nPages active: 448322 \nPages inactive: 438781 \nPages speculative: 9059 \nPages throttled: 0 \nPages wired down: 298599 \n\nCompressor Stats:\nPages used by compressor: 336603 \nPages decompressed: 285822422 \nPages compressed: 347159646 \n\nFile I/O:\nPageins: 512574445 \nPageouts: 1725914 \n\nSystem-wide memory free percentage: 58%"
      },
      "ok": true,
      "power": {
        "ac_power": false,
        "raw": "Now drawing from 'Battery Power'"
      },
      "processes": [
        {
          "command": "/Applications/Cursor.app/Contents/Frameworks/Cursor Helper (Renderer).app/Contents/MacOS/Cursor Helper (Renderer)",
          "cpu_pct": 117.5,
          "noisy": false
        },
        {
          "command": "/System/Library/PrivateFrameworks/SkyLight.framework/Resources/WindowServer",
          "cpu_pct": 29.1,
          "noisy": false
        },
        {
          "command": "/usr/sbin/coreaudiod",
          "cpu_pct": 11.7,
          "noisy": false
        },
        {
          "command": "sshd-session: mattmireles [priv]",
          "cpu_pct": 11.2,
          "noisy": false
        },
        {
          "command": "/private/tmp/dreaded-nights/Dreaded Nights at Morgan's Diner.app/Contents/MacOS/Dreaded Nights at Morgan's Diner",
          "cpu_pct": 7.8,
          "noisy": false
        },
        {
          "command": "/Applications/Cursor.app/Contents/MacOS/Cursor",
          "cpu_pct": 7.2,
          "noisy": false
        },
        {
          "command": "/Applications/Brave Browser.app/Contents/Frameworks/Brave Browser Framework.framework/Versions/149.1.91.168/Helpers/Brave Browser Helper (Renderer).app/Contents/MacOS/Brave Browser Helper (Renderer)",
          "cpu_pct": 6.8,
          "noisy": false
        },
        {
          "command": "/Applications/Cursor.app/Contents/Frameworks/Cursor Helper (GPU).app/Contents/MacOS/Cursor Helper (GPU)",
          "cpu_pct": 5.0,
          "noisy": false
        },
        {
          "command": "/System/Library/CoreServices/WindowManager.app/Contents/MacOS/WindowManager",
          "cpu_pct": 4.5,
          "noisy": false
        },
        {
          "command": "/Applications/Brave Browser.app/Contents/Frameworks/Brave Browser Framework.framework/Versions/149.1.91.168/Helpers/Brave Browser Helper (Renderer).app/Contents/MacOS/Brave Browser Helper (Renderer)",
          "cpu_pct": 4.5,
          "noisy": false
        },
        {
          "command": "/usr/libexec/opendirectoryd",
          "cpu_pct": 4.4,
          "noisy": false
        },
        {
          "command": "/usr/libexec/syspolicyd",
          "cpu_pct": 3.3,
          "noisy": false
        }
      ],
      "quiet": false,
      "swap": {
        "raw": "vm.swapusage: total = 1024.00M  used = 266.94M  free = 757.06M  (encrypted)",
        "used_mb": 266.94
      },
      "target": "mattmireles@m2-air.local",
      "thermal": {
        "ok": true,
        "raw": "Note: No thermal warning level has been recorded\nNote: No performance warning level has been recorded\nNote: No CPU power status has been recorded"
      },
      "thresholds": {
        "max_load_1": 1.5,
        "max_noisy_cpu_pct": 5.0,
        "max_swap_used_mb": 0.0,
        "min_memory_free_pct": 10,
        "noisy_process_patterns": [
          "mds",
          "mdworker",
          "mediaanalysisd",
          "mediaanalysisd-access",
          "photoanalysisd"
        ],
        "require_ac_power": true
      },
      "uptime": "20:01  up 8 days, 21:38, 2 users, load averages: 2.35 3.35 3.70"
    }
  ]
}
